{
"type": "FeatureCollection",
"name": "unique_stations",
"crs": { "type": "name", "properties": { "name": "urn:ogc:def:crs:OGC:1.3:CRS84" } },
"features": [
{ "type": "Feature", "properties": { "id": 0 }, "geometry": { "type": "Point", "coordinates": [ 8.47917, 47.39113 ] } },
{ "type": "Feature", "properties": { "id": 1 }, "geometry": { "type": "Point", "coordinates": [ 8.57437, 47.34812 ] } },
{ "type": "Feature", "properties": { "id": 2 }, "geometry": { "type": "Point", "coordinates": [ 8.53551, 47.35988 ] } },
{ "type": "Feature", "properties": { "id": 3 }, "geometry": { "type": "Point", "coordinates": [ 8.48838, 47.39111 ] } },
{ "type": "Feature", "properties": { "id": 4 }, "geometry": { "type": "Point", "coordinates": [ 8.47743, 47.3603 ] } },
{ "type": "Feature", "properties": { "id": 5 }, "geometry": { "type": "Point", "coordinates": [ 8.53542, 47.36787 ] } },
{ "type": "Feature", "properties": { "id": 6 }, "geometry": { "type": "Point", "coordinates": [ 8.52646, 47.41396 ] } },
{ "type": "Feature", "properties": { "id": 7 }, "geometry": { "type": "Point", "coordinates": [ 8.49414, 47.40894 ] } },
{ "type": "Feature", "properties": { "id": 8 }, "geometry": { "type": "Point", "coordinates": [ 8.48317, 47.41738 ] } },
{ "type": "Feature", "properties": { "id": 9 }, "geometry": { "type": "Point", "coordinates": [ 8.54849, 47.36661 ] } },
{ "type": "Feature", "properties": { "id": 10 }, "geometry": { "type": "Point", "coordinates": [ 8.55784, 47.35934 ] } },
{ "type": "Feature", "properties": { "id": 11 }, "geometry": { "type": "Point", "coordinates": [ 8.51059, 47.39004 ] } },
{ "type": "Feature", "properties": { "id": 12 }, "geometry": { "type": "Point", "coordinates": [ 8.53494, 47.38212 ] } },
{ "type": "Feature", "properties": { "id": 13 }, "geometry": { "type": "Point", "coordinates": [ 8.5562, 47.38625 ] } },
{ "type": "Feature", "properties": { "id": 14 }, "geometry": { "type": "Point", "coordinates": [ 8.50462, 47.39973 ] } },
{ "type": "Feature", "properties": { "id": 15 }, "geometry": { "type": "Point", "coordinates": [ 8.57502, 47.35457 ] } },
{ "type": "Feature", "properties": { "id": 16 }, "geometry": { "type": "Point", "coordinates": [ 8.5204, 47.35786 ] } },
{ "type": "Feature", "properties": { "id": 17 }, "geometry": { "type": "Point", "coordinates": [ 8.53423, 47.35098 ] } },
{ "type": "Feature", "properties": { "id": 18 }, "geometry": { "type": "Point", "coordinates": [ 8.51184, 47.42459 ] } },
{ "type": "Feature", "properties": { "id": 19 }, "geometry": { "type": "Point", "coordinates": [ 8.55009, 47.41096 ] } },
{ "type": "Feature", "properties": { "id": 20 }, "geometry": { "type": "Point", "coordinates": [ 8.52287, 47.41689 ] } },
{ "type": "Feature", "properties": { "id": 21 }, "geometry": { "type": "Point", "coordinates": [ 8.57808, 47.3805 ] } },
{ "type": "Feature", "properties": { "id": 22 }, "geometry": { "type": "Point", "coordinates": [ 8.47731, 47.41345 ] } },
{ "type": "Feature", "properties": { "id": 23 }, "geometry": { "type": "Point", "coordinates": [ 8.54367, 47.42865 ] } },
{ "type": "Feature", "properties": { "id": 24 }, "geometry": { "type": "Point", "coordinates": [ 8.59056, 47.35691 ] } },
{ "type": "Feature", "properties": { "id": 25 }, "geometry": { "type": "Point", "coordinates": [ 8.55817, 47.36673 ] } },
{ "type": "Feature", "properties": { "id": 26 }, "geometry": { "type": "Point", "coordinates": [ 8.47454, 47.38288 ] } },
{ "type": "Feature", "properties": { "id": 27 }, "geometry": { "type": "Point", "coordinates": [ 8.52623, 47.35164 ] } },
{ "type": "Feature", "properties": { "id": 28 }, "geometry": { "type": "Point", "coordinates": [ 8.48391, 47.4123 ] } },
{ "type": "Feature", "properties": { "id": 29 }, "geometry": { "type": "Point", "coordinates": [ 8.53635, 47.42613 ] } },
{ "type": "Feature", "properties": { "id": 30 }, "geometry": { "type": "Point", "coordinates": [ 8.55319, 47.40594 ] } },
{ "type": "Feature", "properties": { "id": 31 }, "geometry": { "type": "Point", "coordinates": [ 8.51856, 47.33305 ] } },
{ "type": "Feature", "properties": { "id": 32 }, "geometry": { "type": "Point", "coordinates": [ 8.5127, 47.32824 ] } },
{ "type": "Feature", "properties": { "id": 33 }, "geometry": { "type": "Point", "coordinates": [ 8.53197, 47.35147 ] } },
{ "type": "Feature", "properties": { "id": 34 }, "geometry": { "type": "Point", "coordinates": [ 8.51915, 47.33513 ] } },
{ "type": "Feature", "properties": { "id": 35 }, "geometry": { "type": "Point", "coordinates": [ 8.52035, 47.33697 ] } }
]
}
